Workbook

Sheet Вводные
B1: Модель прибыльности отеля — исходные данные
B2: Корпоративный отель на 8 номеров, Бишкек · данные интервью с владельцем, не аудированы · деньги — тыс. сом в месяц, если не указано иное
B4: Как читать
B5: Синий шрифт — вводимое значение (меняйте только их) | C5: Листы: База → Юнит_экономика → Стресс_тесты → Мост_прибыли → Карта → Сверка. Параметры шоков и сценариев лежат на листах Стресс_тесты и Мост_прибыли (тоже синие).
B6: Чёрный шрифт — формула
B7: Зелёный шрифт — ссылка на другой лист
B8: Жёлтая заливка — допущение автора кейса (владелец его не называл)
B10: Параметр | C10: Значение | D10: Ед. | E10: Тип данных | F10: Источник / комментарий
B11: Объект и продажи
B12: Номеров | C12: 8 | D12: шт | E12: Заявлено владельцем | F12: Шапка кейса
B13: Дней в году (для номеро-ночей) | C13: 365 | D13: дней | E13: Расчёт | F13: Номеро-ночей в месяц = номера × 365 ÷ 12 = 243,3
B14: Загрузка | C14: 0.94 | D14: % | E14: Заявлено владельцем | F14: Раздел 3; три цифры (загрузка, ADR, выручка) между собой не сходятся — раздел 4
B15: ADR — прейскурантная средняя цена за ночь | C15: 3755 | D15: сом | E15: Заявлено владельцем | F15: Раздел 2
B16: Выручка в месяц — опорная точка модели | C16: 800 | D16: тыс. сом/мес | E16: Заявлено владельцем | F16: По записям владельца; модель привязана к ней, а не к загрузка × ADR (раздел 4)
B17: Постоянные затраты
B18: Аренда | C18: 350 | D18: тыс. сом/мес | E18: Заявлено владельцем | F18: Фиксирована, без индексации первые 5 лет; срок договора 3 года
B19: ФОТ и взносы — как принято в модели | C19: 102.3 | D19: тыс. сом/мес | E19: Допущение кейса | F19: Раздел 2: «carried at 102.3k»; из них названо владельцем 100 тыс., остальное — допущение кейса
B20: Электричество (среднемесячное) | C20: 60 | D20: тыс. сом/мес | E20: Заявлено владельцем | F20: В месяцы отопления до 100 тыс.
B21: Вода | C21: 6.5 | D21: тыс. сом/мес | E21: Заявлено владельцем | F21: График «куда уходят 100 сом» (раздел 2)
B22: ФОТ, названный владельцем (справочно) | C22: 100 | D22: тыс. сом/мес | E22: Заявлено владельцем | F22: Для стресс-теста «взносы сверху»
B23: Ставка взносов в Соцфонд (справочно) | C23: 0.1225 | D23: % | E23: Заявлено владельцем | F23: Владелец не уточнил, входят ли взносы в ФОТ 100 тыс.
B24: Расходники (потребляемые материалы)
B25: Расходники — нижняя граница | C25: 15 | D25: тыс. сом/мес | E25: Заявлено владельцем | F25: Диапазон 15–20 тыс. в месяц
B26: Расходники — верхняя граница | C26: 20 | D26: тыс. сом/мес | E26: Заявлено владельцем
B27: Расходники — принято в модели | C27: =AVERAGE(C25:C26) -> 17.5 | D27: тыс. сом/мес | E27: Допущение кейса | F27: Середина диапазона (допущение кейса)
B28: Каналы продаж и комиссия
B29: Доля ночей через Booking.com | C29: 0.2 | D29: % | E29: Заявлено владельцем | F29: ≈20% ночей
B30: Доля ночей из соцсетей | C30: 0.03 | D30: % | E30: Заявлено владельцем | F30: ≈3% ночей, без комиссии
B31: Доля неконтрактных ночей | C31: =C29+C30 -> 0.23 | D31: % | E31: Расчёт | F31: Booking.com + соцсети = 23%
B32: Доля контрактных ночей | C32: =1-C31 -> 0.77 | D32: % | E32: Расчёт | F32: Реально 77–80%; в модели 77%
B33: Комиссия Booking.com | C33: 0.23 | D33: % | E33: Заявлено владельцем | F33: 23% реализованной цены
B34: Комиссия в % от выручки | C34: =C29*C33 -> 0.046 | D34: % | E34: Расчёт | F34: Доля Booking × комиссия = 4,6% (цена Booking принята равной средней)
B35: Единый налог
B36: Доля поступлений наличными | C36: 0.15 | D36: % | E36: Допущение кейса | F36: Допущение кейса
B37: Ставка с наличных | C37: 0.06 | D37: % | E37: Заявлено владельцем
B38: Ставка с безналичных | C38: 0.04 | D38: % | E38: Заявлено владельцем
B39: Единый налог — в среднем от выручки | C39: =C36*C37+(1-C36)*C38 -> 0.043 | D39: % | E39: Расчёт | F39: Смешанная ставка 4,3%
B40: Переменные потери с выручки: комиссия + налог | C40: =$C$34+C39 -> 0.089 | D40: % | E40: Расчёт | F40: 8,9% — «1 − 8,9%» в формулах раздела 3
B41: Справочно
B42: Резерв FF&E (мебель, оборудование) | C42: 0.05 | D42: % | E42: Допущение кейса | F42: Раздел 2: после резерва владельцу остаётся 152,5 тыс. Используется только для справки

Sheet База
B1: База: загрузка, ADR и выручка + месячный P&L владельца
B2: Все цифры — формулы от листа «Вводные» · тыс. сом в месяц, если не указано иное
B4: A. Мощность и сверка трёх заявленных цифр (раздел 4)
B5: Показатель | C5: Значение | D5: Ед. | E5: Как считается
B6: Номеро-ночей в месяц (доступно) | C6: =Вводные!$C$12*Вводные!$C$13/12 -> 243.33333 | D6: ночей | E6: номера × дней в году ÷ 12
B7: Проданных ночей в месяц | C7: =$C$6*Вводные!$C$14 -> 228.73333 | D7: ночей | E7: доступные ночи × загрузка
B8: Расчётная выручка: загрузка × ADR × номеро-ночи | C8: =Вводные!$C$14*Вводные!$C$15*$C$6/1000 -> 858.89367 | D8: тыс. сом/мес | E8: 858,9 в кейсе
B9: Заявленная выручка | C9: =Вводные!$C$16 -> 800 | D9: тыс. сом/мес | E9: якорь модели
B10: Разрыв | C10: =$C$8-$C$9 -> 58.893667 | D10: тыс. сом/мес
B11: Коэффициент приведения k = заявленная ÷ расчётная | C11: =$C$9/$C$8 -> 0.93143078 | D11: коэф. | E11: лишь масштабирует загрузка × ADR к заявленной выручке
B12: Разрыв в год | C12: =$C$10*12/1000 -> 0.706724 | D12: млн сом
B13: ADR, следующий из выручки и загрузки | C13: =$C$9*1000/$C$7 -> 3497.5226 | D13: сом | E13: используется для комиссии с ночи Booking (рычаг 3)
B14: Загрузка, следующая из выручки и ADR | C14: =$C$9*1000/(Вводные!$C$15*$C$6) -> 0.87554494 | D14: %
B16: B. Месячный P&L владельца (после аренды, всех затрат и единого налога)
B17: Статья | C17: Значение | D17: Ед. | E17: Как считается
B18: Выручка | C18: =Вводные!$C$16 -> 800 | D18: тыс. сом/мес
B19: Аренда | C19: =Вводные!$C$18 -> 350 | D19: тыс. сом/мес
B20: ФОТ и взносы | C20: =Вводные!$C$19 -> 102.3 | D20: тыс. сом/мес
B21: Электричество | C21: =Вводные!$C$20 -> 60 | D21: тыс. сом/мес
B22: Вода | C22: =Вводные!$C$21 -> 6.5 | D22: тыс. сом/мес
B23: Постоянные затраты, итого | C23: =SUM($C$19:$C$22) -> 518.8 | D23: тыс. сом/мес | E23: аренда + ФОТ + электричество + вода = 518,8
B24: Расходники | C24: =Вводные!$C$27 -> 17.5 | D24: тыс. сом/мес | E24: растут с загрузкой
B25: Комиссия Booking.com | C25: =$C$18*Вводные!$C$34 -> 36.8 | D25: тыс. сом/мес | E25: выручка × 4,6% = 36,8
B26: Затраты, итого | C26: =$C$23+$C$24+$C$25 -> 573.1 | D26: тыс. сом/мес | E26: 573,1 в кейсе
B27: Единый налог | C27: =$C$18*Вводные!$C$39 -> 34.4 | D27: тыс. сом/мес | E27: выручка × 4,3% = 34,4
B28: Прибыль владельца после налога | C28: =$C$18-$C$26-$C$27 -> 192.5 | D28: тыс. сом/мес | E28: 192,5 в кейсе
B29: Маржа после единого налога | C29: =$C$28/$C$18 -> 0.240625 | D29: % | E29: 24,1% в кейсе (заявлено владельцем 25%)
B30: Маржа до единого налога | C30: =($C$18-$C$26)/$C$18 -> 0.283625 | D30: % | E30: в тексте кейса «≈29%», по цифрам кейса выходит 28,4%
B31: Резерв FF&E | C31: =$C$18*Вводные!$C$42 -> 40 | D31: тыс. сом/мес | E31: справочно
B32: Прибыль после резерва FF&E | C32: =$C$28-$C$31 -> 152.5 | D32: тыс. сом/мес | E32: 152,5 в кейсе
B33: Постоянные затраты в % выручки | C33: =$C$23/$C$18 -> 0.6485 | D33: % | E33: «65% выручки» в кейсе
B34: Аренда в % выручки | C34: =$C$19/$C$18 -> 0.4375 | D34: % | E34: 43,8% в кейсе
B35: Аренда ÷ прибыль владельца | C35: =$C$19/$C$28 -> 1.8181818 | D35: раз | E35: 1,8× в кейсе

Sheet Юнит_экономика
B1: Юнит-экономика: на проданную ночь и на номер
B2: Раздел 2 кейса · на ночь — сом, на номер — тыс. сом в месяц · все ячейки — формулы
B4: 1. На проданную ночь, по заявленному ADR
B5: Статья | C5: Значение | D5: Ед. | E5: Как считается
B6: Цена (ADR) | C6: =Вводные!$C$15 -> 3755 | D6: сом | E6: прейскурантный ADR
B7: Расходники | C7: =-База!$C$24*1000/База!$C$7 -> -76.508307 | D7: сом | E7: расходники в месяц ÷ проданные ночи
B8: Комиссия Booking.com, в среднем | C8: =-$C$6*Вводные!$C$34 -> -172.73 | D8: сом | E8: ADR × 4,6% (23% × 20% ночей)
B9: Вклад до единого налога | C9: =SUM($C$6:$C$8) -> 3505.7617 | D9: сом | E9: цена − расходники − комиссия
B10: Единый налог | C10: =-$C$6*Вводные!$C$39 -> -161.465 | D10: сом | E10: ADR × 4,3%
B11: Вклад после единого налога | C11: =$C$9+$C$10 -> 3344.2967 | D11: сом
B12: Постоянные затраты на проданную ночь | C12: =-База!$C$23*1000/База!$C$7 -> -2268.1434 | D12: сом | E12: постоянные затраты ÷ проданные ночи
B13: Прибыль за ночь по заявленному ADR | C13: =$C$11+$C$12 -> 1076.1533 | D13: сом
B14: Сверка с фактической выручкой (×k) | C14: =$C$15-$C$13 -> -234.56192 | D14: сом | E14: владелец реально получает меньше: выручка = 800 тыс., а не загрузка × ADR
B15: Прибыль владельца за проданную ночь | C15: =База!$C$28*1000/База!$C$7 -> 841.59137 | D15: сом | E15: прибыль владельца в месяц ÷ проданные ночи
B16: Контроль: −ADR × (1 − k) × (1 − комиссия − налог) | C16: =-$C$6*(1-База!$C$11)*(1-Вводные!$C$40) -> -234.56192 | E16: должно совпасть со строкой «Сверка с фактической выручкой»
B18: 2. На номер в месяц
B19: Статья | C19: Значение | D19: Ед. | E19: Как считается
B20: Выручка | C20: =База!$C$18/Вводные!$C$12 -> 100 | D20: тыс. сом/мес | E20: ÷ число номеров
B21: Затраты | C21: =-База!$C$26/Вводные!$C$12 -> -71.6375 | D21: тыс. сом/мес
B22: Единый налог | C22: =-База!$C$27/Вводные!$C$12 -> -4.3 | D22: тыс. сом/мес
B23: Прибыль владельца на номер | C23: =SUM($C$20:$C$22) -> 24.0625 | D23: тыс. сом/мес
B25: 3. Куда уходят каждые 100 сом выручки
B26: Статья | C26: тыс. сом/мес | D26: На 100 сом | E26: Комментарий
B27: Выручка | C27: =База!$C$18 -> 800 | D27: =C27/$C$27*100 -> 100
B28: Аренда | C28: =-База!$C$19 -> -350 | D28: =C28/$C$27*100 -> -43.75 | E28: самая большая статья
B29: ФОТ и взносы | C29: =-База!$C$20 -> -102.3 | D29: =C29/$C$27*100 -> -12.7875
B30: Электричество | C30: =-База!$C$21 -> -60 | D30: =C30/$C$27*100 -> -7.5 | E30: зимой до 100 тыс.
B31: Вода | C31: =-База!$C$22 -> -6.5 | D31: =C31/$C$27*100 -> -0.8125
B32: Расходники | C32: =-База!$C$24 -> -17.5 | D32: =C32/$C$27*100 -> -2.1875
B33: Комиссия Booking.com | C33: =-База!$C$25 -> -36.8 | D33: =C33/$C$27*100 -> -4.6
B34: Единый налог | C34: =-База!$C$27 -> -34.4 | D34: =C34/$C$27*100 -> -4.3
B35: Прибыль владельца | C35: =SUM(C27:C34) -> 192.5 | D35: =C35/$C$27*100 -> 24.0625 | E35: 24 сома из каждых 100 доходят до владельца

Sheet Стресс_тесты
B1: Стресс-тесты: шоки по отдельности
B2: Раздел 5 кейса · прибыль владельца после единого налога, тыс. сом в месяц · каждая строка — набор относительных изменений к базе
B4: 1. Размер шоков (меняйте значения — таблица пересчитается)
B5: Параметр | C5: Значение | D5: Ед.
B6: Падение выручки — шок 1 | C6: 0.1 | D6: % | F6: Потеря операторов: расходники и налог снижаются вместе с выручкой, комиссия Booking.com остаётся (комиссии нет в контрактной выручке).
B7: Падение выручки — шок 2 | C7: 0.15 | D7: % | F7: Выручка −10% / −15%: расходники, комиссия и налог снижаются пропорционально выручке.
B8: Доля двух мобильных операторов в выручке | C8: 0.08 | D8: % | F8: Строки 8–10 таблицы — расширения: два шока из текста кейса и один комбинированный (мой, в кейсе его нет).
B9: Рост аренды | C9: 0.1 | D9: %
B10: Рост электричества | C10: 0.2 | D10: %
B11: Зарплата управляющего (труд владельца не оплачивается) | C11: 60 | D11: тыс./мес
B12: Электричество в месяц отопления | C12: 100 | D12: тыс./мес
B14: 2. Таблица шоков | C14: ← входные изменения (синие — ввод; чёрные — формулы) | I14: ← результат, тыс. сом/мес
B15: Шок | C15: Δ выручки | D15: Δ расходников | E15: Δ комиссии | F15: Δ аренды | G15: Δ электричества | H15: Прочие пост., тыс. | I15: Выручка | J15: Постоянные | K15: Расходники | L15: Комиссия | M15: Налог | N15: Прибыль владельца | O15: Δ, тыс. | P15: Δ, % | Q15: Маржа | R15: Рычаг, × | S15: Источник
B16: ="База" -> База | C16: 0 | D16: =C16 -> 0 | E16: =C16 -> 0 | F16: 0 | G16: 0 | H16: 0 | I16: =База!$C$18*(1+C16) -> 800 | J16: =База!$C$23+Вводные!$C$18*F16+Вводные!$C$20*G16+H16 -> 518.8 | K16: =База!$C$24*(1+D16) -> 17.5 | L16: =База!$C$25*(1+E16) -> 36.8 | M16: =I16*Вводные!$C$39 -> 34.4 | N16: =I16-J16-K16-L16-M16 -> 192.5 | O16: =ROUND(N16-База!$C$28,9) -> 0 | P16: =O16/База!$C$28 -> 0 | Q16: =N16/I16 -> 0.240625 | R16: =IF(AND(C16<>0,F16=0,G16=0,H16=0),P16/C16,"–") -> – | S16: кейс
B17: ="Выручка −"&TEXT(Стресс_тесты!$C$6,"0%") -> Выручка −10% | C17: =-Стресс_тесты!$C$6 -> -0.1 | D17: =C17 -> -0.1 | E17: =C17 -> -0.1 | F17: 0 | G17: 0 | H17: 0 | I17: =База!$C$18*(1+C17) -> 720 | J17: =База!$C$23+Вводные!$C$18*F17+Вводные!$C$20*G17+H17 -> 518.8 | K17: =База!$C$24*(1+D17) -> 15.75 | L17: =База!$C$25*(1+E17) -> 33.12 | M17: =I17*Вводные!$C$39 -> 30.96 | N17: =I17-J17-K17-L17-M17 -> 121.37 | O17: =ROUND(N17-База!$C$28,9) -> -71.13 | P17: =O17/База!$C$28 -> -0.36950649 | Q17: =N17/I17 -> 0.16856944 | R17: =IF(AND(C17<>0,F17=0,G17=0,H17=0),P17/C17,"–") -> 3.6950649 | S17: кейс
B18: ="Выручка −"&TEXT(Стресс_тесты!$C$7,"0%") -> Выручка −15% | C18: =-Стресс_тесты!$C$7 -> -0.15 | D18: =C18 -> -0.15 | E18: =C18 -> -0.15 | F18: 0 | G18: 0 | H18: 0 | I18: =База!$C$18*(1+C18) -> 680 | J18: =База!$C$23+Вводные!$C$18*F18+Вводные!$C$20*G18+H18 -> 518.8 | K18: =База!$C$24*(1+D18) -> 14.875 | L18: =База!$C$25*(1+E18) -> 31.28 | M18: =I18*Вводные!$C$39 -> 29.24 | N18: =I18-J18-K18-L18-M18 -> 85.805 | O18: =ROUND(N18-База!$C$28,9) -> -106.695 | P18: =O18/База!$C$28 -> -0.55425974 | Q18: =N18/I18 -> 0.12618382 | R18: =IF(AND(C18<>0,F18=0,G18=0,H18=0),P18/C18,"–") -> 3.6950649 | S18: кейс
B19: ="Потеря двух мобильных операторов (−"&TEXT(Стресс_тесты!$C$8,"0%")&" выручки)" -> Потеря двух мобильных операторов (−8% выручки) | C19: =-Стресс_тесты!$C$8 -> -0.08 | D19: =C19 -> -0.08 | E19: 0 | F19: 0 | G19: 0 | H19: 0 | I19: =База!$C$18*(1+C19) -> 736 | J19: =База!$C$23+Вводные!$C$18*F19+Вводные!$C$20*G19+H19 -> 518.8 | K19: =База!$C$24*(1+D19) -> 16.1 | L19: =База!$C$25*(1+E19) -> 36.8 | M19: =I19*Вводные!$C$39 -> 31.648 | N19: =I19-J19-K19-L19-M19 -> 132.652 | O19: =ROUND(N19-База!$C$28,9) -> -59.848 | P19: =O19/База!$C$28 -> -0.3108987 | Q19: =N19/I19 -> 0.1802337 | R19: =IF(AND(C19<>0,F19=0,G19=0,H19=0),P19/C19,"–") -> 3.8862338 | S19: кейс
B20: ="Аренда +"&TEXT(Стресс_тесты!$C$9,"0%") -> Аренда +10% | C20: 0 | D20: =C20 -> 0 | E20: =C20 -> 0 | F20: =Стресс_тесты!$C$9 -> 0.1 | G20: 0 | H20: 0 | I20: =База!$C$18*(1+C20) -> 800 | J20: =База!$C$23+Вводные!$C$18*F20+Вводные!$C$20*G20+H20 -> 553.8 | K20: =База!$C$24*(1+D20) -> 17.5 | L20: =База!$C$25*(1+E20) -> 36.8 | M20: =I20*Вводные!$C$39 -> 34.4 | N20: =I20-J20-K20-L20-M20 -> 157.5 | O20: =ROUND(N20-База!$C$28,9) -> -35 | P20: =O20/База!$C$28 -> -0.18181818 | Q20: =N20/I20 -> 0.196875 | R20: =IF(AND(C20<>0,F20=0,G20=0,H20=0),P20/C20,"–") -> – | S20: кейс
B21: ="Электричество +"&TEXT(Стресс_тесты!$C$10,"0%") -> Электричество +20% | C21: 0 | D21: =C21 -> 0 | E21: =C21 -> 0 | F21: 0 | G21: =Стресс_тесты!$C$10 -> 0.2 | H21: 0 | I21: =База!$C$18*(1+C21) -> 800 | J21: =База!$C$23+Вводные!$C$18*F21+Вводные!$C$20*G21+H21 -> 530.8 | K21: =База!$C$24*(1+D21) -> 17.5 | L21: =База!$C$25*(1+E21) -> 36.8 | M21: =I21*Вводные!$C$39 -> 34.4 | N21: =I21-J21-K21-L21-M21 -> 180.5 | O21: =ROUND(N21-База!$C$28,9) -> -12 | P21: =O21/База!$C$28 -> -0.062337662 | Q21: =N21/I21 -> 0.225625 | R21: =IF(AND(C21<>0,F21=0,G21=0,H21=0),P21/C21,"–") -> – | S21: кейс
B22: ="Управляющий за "&TEXT(Стресс_тесты!$C$11,"0")&" тыс." -> Управляющий за 60 тыс. | C22: 0 | D22: =C22 -> 0 | E22: =C22 -> 0 | F22: 0 | G22: 0 | H22: =Стресс_тесты!$C$11 -> 60 | I22: =База!$C$18*(1+C22) -> 800 | J22: =База!$C$23+Вводные!$C$18*F22+Вводные!$C$20*G22+H22 -> 578.8 | K22: =База!$C$24*(1+D22) -> 17.5 | L22: =База!$C$25*(1+E22) -> 36.8 | M22: =I22*Вводные!$C$39 -> 34.4 | N22: =I22-J22-K22-L22-M22 -> 132.5 | O22: =ROUND(N22-База!$C$28,9) -> -60 | P22: =O22/База!$C$28 -> -0.31168831 | Q22: =N22/I22 -> 0.165625 | R22: =IF(AND(C22<>0,F22=0,G22=0,H22=0),P22/C22,"–") -> – | S22: кейс
B23: ="Электричество "&TEXT(Стресс_тесты!$C$12,"0")&" тыс. (месяц отопления)" -> Электричество 100 тыс. (месяц отопления) | C23: 0 | D23: =C23 -> 0 | E23: =C23 -> 0 | F23: 0 | G23: =Стресс_тесты!$C$12/Вводные!$C$20-1 -> 0.66666667 | H23: 0 | I23: =База!$C$18*(1+C23) -> 800 | J23: =База!$C$23+Вводные!$C$18*F23+Вводные!$C$20*G23+H23 -> 558.8 | K23: =База!$C$24*(1+D23) -> 17.5 | L23: =База!$C$25*(1+E23) -> 36.8 | M23: =I23*Вводные!$C$39 -> 34.4 | N23: =I23-J23-K23-L23-M23 -> 152.5 | O23: =ROUND(N23-База!$C$28,9) -> -40 | P23: =O23/База!$C$28 -> -0.20779221 | Q23: =N23/I23 -> 0.190625 | R23: =IF(AND(C23<>0,F23=0,G23=0,H23=0),P23/C23,"–") -> – | S23: расширение: текст раздела 5
B24: ="Взносы 12,25% начисляются сверху на ФОТ" -> Взносы 12,25% начисляются сверху на ФОТ | C24: 0 | D24: =C24 -> 0 | E24: =C24 -> 0 | F24: 0 | G24: 0 | H24: =Вводные!$C$22*Вводные!$C$23-(Вводные!$C$19-Вводные!$C$22) -> 9.95 | I24: =База!$C$18*(1+C24) -> 800 | J24: =База!$C$23+Вводные!$C$18*F24+Вводные!$C$20*G24+H24 -> 528.75 | K24: =База!$C$24*(1+D24) -> 17.5 | L24: =База!$C$25*(1+E24) -> 36.8 | M24: =I24*Вводные!$C$39 -> 34.4 | N24: =I24-J24-K24-L24-M24 -> 182.55 | O24: =ROUND(N24-База!$C$28,9) -> -9.95 | P24: =O24/База!$C$28 -> -0.051688312 | Q24: =N24/I24 -> 0.2281875 | R24: =IF(AND(C24<>0,F24=0,G24=0,H24=0),P24/C24,"–") -> – | S24: расширение: текст раздела 2
B25: ="Комбинированный: выручка −"&TEXT(Стресс_тесты!$C$6,"0%")&" и аренда +"&TEXT(Стресс_тесты!$C$9,"0%") -> Комбинированный: выручка −10% и аренда +10% | C25: =-Стресс_тесты!$C$6 -> -0.1 | D25: =C25 -> -0.1 | E25: =C25 -> -0.1 | F25: =Стресс_тесты!$C$9 -> 0.1 | G25: 0 | H25: 0 | I25: =База!$C$18*(1+C25) -> 720 | J25: =База!$C$23+Вводные!$C$18*F25+Вводные!$C$20*G25+H25 -> 553.8 | K25: =База!$C$24*(1+D25) -> 15.75 | L25: =База!$C$25*(1+E25) -> 33.12 | M25: =I25*Вводные!$C$39 -> 30.96 | N25: =I25-J25-K25-L25-M25 -> 86.37 | O25: =ROUND(N25-База!$C$28,9) -> -106.13 | P25: =O25/База!$C$28 -> -0.55132468 | Q25: =N25/I25 -> 0.11995833 | R25: =IF(AND(C25<>0,F25=0,G25=0,H25=0),P25/C25,"–") -> – | S25: расширение: моё, в кейсе нет
B27: Рычаг, × = изменение прибыли в % ÷ изменение выручки в %: постоянные затраты 518,8 тыс. делают удар по прибыли в 3,7–3,9 раза сильнее, чем по выручке.
B28: Обратный стресс-тест: выручка может упасть на | C28: =-Карта!$C$16 -> 0.27063124 | D28: прежде чем прибыль владельца станет нулевой (то же, что запас прочности по загрузке на листе «Карта»)

Sheet Мост_прибыли
B1: Мост прибыли: рычаги, сценарии, окупаемость
B2: Раздел 6 кейса · эффекты — тыс. сом в месяц в «беговом» темпе; разовые затраты — оценки без котировок
B4: 1. Параметры сценариев (допущения кейса)
B5: Допущение | C5: Ед. | D5: Консервативный | E5: Базовый | F5: Апсайд
B6: Рост цены на неконтрактных ночах | C6: % | D6: 0.04 | E6: 0.08 | F6: 0.08
B7: Потеря объёма на неконтрактных ночах | C7: % | D7: 0.03 | E7: 0.02 | F7: 0.02
B8: Ночей ушло с Booking.com и заполнено по той же цене | C8: п.п. | D8: 2 | E8: 4 | F8: 4
B9: Экономия электричества | C9: % | D9: 0.05 | E9: 0.1 | F9: 0.1
B10: Пересмотр цен в контрактах при пролонгации (1 — да, 0 — нет) | C10: флаг | D10: 0 | E10: 0 | F10: 1
B12: 2. Общие параметры рычагов
B13: Параметр | C13: Ед. | D13: Значение
B14: Пересмотр цены при пролонгации контракта | C14: % | D14: 0.04
B15: Доля контрактной выручки, где цена пересматривается | C15: % | D15: 0.9
B16: Потеря контрактного объёма | C16: % | D16: 0.01
B17: Разовые затраты: рычаг 2 — цены на неконтрактных ночах | C17: тыс. сом | D17: 20
B18: Разовые затраты: рычаг 5 — энергосбережение | C18: тыс. сом | D18: 120
B19: Разовые затраты: гигиена — персонал и SOP | C19: тыс. сом | D19: 10
B20: Разовые затраты: гигиена — линия прямых броней | C20: тыс. сом | D20: 30
B21: Ежемесячные затраты: персонал и SOP | C21: тыс./мес | D21: 3
B22: Ежемесячные затраты: линия прямых броней | C22: тыс./мес | D22: 5
B23: Рычаг 1: возможный пересмотр аренды — нижняя оценка | C23: % | D23: 0.05
B24: Рычаг 1: возможный пересмотр аренды — верхняя оценка | C24: % | D24: 0.1
B25: Горизонт оценки | C25: мес. | D25: 36
B26: Выручка неконтрактных ночей (Booking + соцсети) | C26: тыс./мес | D26: =База!$C$18*Вводные!$C$31 -> 184
B27: Выручка контрактных ночей | C27: тыс./мес | D27: =База!$C$18*Вводные!$C$32 -> 616
B28: Комиссия с одной ночи через Booking.com | C28: сом | D28: =Вводные!$C$33*База!$C$13 -> 804.4302
B29: Разовые затраты, итого | C29: тыс. сом | D29: =Мост_прибыли!$D$17+Мост_прибыли!$D$18+Мост_прибыли!$D$19+Мост_прибыли!$D$20 -> 180
B31: 3. Эффекты рычагов, тыс. сом в месяц (операционная прибыль до единого налога)
B32: Рычаг / показатель | C32: Ед. | D32: Консервативный | E32: Базовый | F32: Апсайд
B33: Вспомогательно: изменение выручки на неконтрактных ночах | C33: % | D33: =(1+D$6)*(1-D$7)-1 -> 0.0088 | E33: =(1+E$6)*(1-E$7)-1 -> 0.0584 | F33: =(1+F$6)*(1-F$7)-1 -> 0.0584 | H33: (1 + цена) × (1 − потеря объёма) − 1
B34: Рычаг 2. Цены на неконтрактных ночах | C34: тыс./мес | D34: =Мост_прибыли!$D$26*D33-База!$C$25*D33+База!$C$24*Вводные!$C$31*D$7 -> 1.41611 | E34: =Мост_прибыли!$D$26*E33-База!$C$25*E33+База!$C$24*Вводные!$C$31*E$7 -> 8.67698 | F34: =Мост_прибыли!$D$26*F33-База!$C$25*F33+База!$C$24*Вводные!$C$31*F$7 -> 8.67698 | H34: Δвыручки − Δкомиссии Booking.com + экономия расходников на потерянных ночах
B35: Рычаг 3. Микс каналов (меньше Booking.com) | C35: тыс./мес | D35: =D$8/100*База!$C$6*Мост_прибыли!$D$28/1000 -> 3.9148936 | E35: =E$8/100*База!$C$6*Мост_прибыли!$D$28/1000 -> 7.8297872 | F35: =F$8/100*База!$C$6*Мост_прибыли!$D$28/1000 -> 7.8297872 | H35: пункты × номеро-ночи × комиссия с ночи (≈804 сом); ночи заполняются по той же цене
B36: Рычаг 5. Энергия | C36: тыс./мес | D36: =Вводные!$C$20*D$9 -> 3 | E36: =Вводные!$C$20*E$9 -> 6 | F36: =Вводные!$C$20*F$9 -> 6 | H36: электричество × экономия
B37: Гигиена: персонал и SOP | C37: тыс./мес | D37: =-Мост_прибыли!$D$21 -> -3 | E37: =-Мост_прибыли!$D$21 -> -3 | F37: =-Мост_прибыли!$D$21 -> -3 | H37: затраты учтены, выгода не считается
B38: Гигиена: линия прямых броней | C38: тыс./мес | D38: =-Мост_прибыли!$D$22 -> -5 | E38: =-Мост_прибыли!$D$22 -> -5 | F38: =-Мост_прибыли!$D$22 -> -5 | H38: затраты учтены, выгода не считается
B39: Рычаг 4. Пересмотр цен в контрактах (апсайд) | C39: тыс./мес | D39: =D$10*(Мост_прибыли!$D$27*Мост_прибыли!$D$15*Мост_прибыли!$D$14-Мост_прибыли!$D$27*Мост_прибыли!$D$16+База!$C$24*Вводные!$C$32*Мост_прибыли!$D$16) -> 0 | E39: =E$10*(Мост_прибыли!$D$27*Мост_прибыли!$D$15*Мост_прибыли!$D$14-Мост_прибыли!$D$27*Мост_прибыли!$D$16+База!$C$24*Вводные!$C$32*Мост_прибыли!$D$16) -> 0 | F39: =F$10*(Мост_прибыли!$D$27*Мост_прибыли!$D$15*Мост_прибыли!$D$14-Мост_прибыли!$D$27*Мост_прибыли!$D$16+База!$C$24*Вводные!$C$32*Мост_прибыли!$D$16) -> 16.15075 | H39: +4% на 90% контрактной выручки − потеря 1% объёма + экономия расходников
B40: Δ операционной прибыли до налога | C40: тыс./мес | D40: =SUM(D34:D39) -> 0.33100362 | E40: =SUM(E34:E39) -> 14.506767 | F40: =SUM(F34:F39) -> 30.657517
B41: Вспомогательно: Δ выручки (база для налога) | C41: тыс./мес | D41: =Мост_прибыли!$D$26*D33+D$10*(Мост_прибыли!$D$27*Мост_прибыли!$D$15*Мост_прибыли!$D$14-Мост_прибыли!$D$27*Мост_прибыли!$D$16) -> 1.6192 | E41: =Мост_прибыли!$D$26*E33+E$10*(Мост_прибыли!$D$27*Мост_прибыли!$D$15*Мост_прибыли!$D$14-Мост_прибыли!$D$27*Мост_прибыли!$D$16) -> 10.7456 | F41: =Мост_прибыли!$D$26*F33+F$10*(Мост_прибыли!$D$27*Мост_прибыли!$D$15*Мост_прибыли!$D$14-Мост_прибыли!$D$27*Мост_прибыли!$D$16) -> 26.7616 | H41: налог платится только с изменения выручки; рычаги 3, 5 и гигиена выручку не меняют
B42: Налог с дополнительной выручки | C42: тыс./мес | D42: =-D41*Вводные!$C$39 -> -0.0696256 | E42: =-E41*Вводные!$C$39 -> -0.4620608 | F42: =-F41*Вводные!$C$39 -> -1.1507488
B43: Δ прибыли владельца после налога | C43: тыс./мес | D43: =D40+D42 -> 0.26137802 | E43: =E40+E42 -> 14.044706 | F43: =F40+F42 -> 29.506768
B44: Прибыль владельца после программы | C44: тыс./мес | D44: =База!$C$28+D43 -> 192.76138 | E44: =База!$C$28+E43 -> 206.54471 | F44: =База!$C$28+F43 -> 222.00677
B45: Рост к текущей прибыли | C45: % | D45: =D43/База!$C$28 -> 0.0013578079 | E45: =E43/База!$C$28 -> 0.072959514 | F45: =F43/База!$C$28 -> 0.15328191
B46: Разовые затраты | C46: тыс. сом | D46: =Мост_прибыли!$D$29 -> 180 | E46: =Мост_прибыли!$D$29 -> 180 | F46: =Мост_прибыли!$D$29 -> 180 | H46: 20 + 120 + 10 + 30
B47: Окупаемость разовых затрат | C47: мес. | D47: =IF(D43*Мост_прибыли!$D$25>=D46,D46/D43,"не достигается") -> не достигается | E47: =IF(E43*Мост_прибыли!$D$25>=E46,E46/E43,"не достигается") -> 12.816217 | F47: =IF(F43*Мост_прибыли!$D$25>=F46,F46/F43,"не достигается") -> 6.1002953 | H47: разовые затраты ÷ Δ прибыли после налога; «не достигается», если не окупаются за горизонт
B48: Чистый эффект за горизонт | C48: тыс. сом | D48: =D43*Мост_прибыли!$D$25-D46 -> -170.59039 | E48: =E43*Мост_прибыли!$D$25-E46 -> 325.60943 | F48: =F43*Мост_прибыли!$D$25-F46 -> 882.24366 | H48: Δ после налога × горизонт − разовые затраты
B50: 4. Рычаг 1 (вне моста) и точка остановки рычага 4
B51: Показатель | C51: Ед. | D51: Нижняя оценка | E51: Верхняя оценка
B52: Защита аренды: пересмотр, которого удаётся избежать | C52: тыс./мес | D52: =Вводные!$C$18*Мост_прибыли!$D$23 -> 17.5 | E52: =Вводные!$C$18*Мост_прибыли!$D$24 -> 35
B53: То же за горизонт оценки | C53: тыс. сом | D53: =Мост_прибыли!$D$52*Мост_прибыли!$D$25 -> 630 | E53: =Мост_прибыли!$E$52*Мост_прибыли!$D$25 -> 1260
B54: Потеря контрактного объёма, при которой рычаг 4 перестаёт приносить прибыль | C54: % | D54: =Мост_прибыли!$D$27*Мост_прибыли!$D$15*Мост_прибыли!$D$14/(Мост_прибыли!$D$27-База!$C$24*Вводные!$C$32) -> 0.036805112 | E54: ← порог остановки (3,7%)
B56: 5. Мост прибыли владельца после налога, тыс. сом/мес (база и апсайд раздельно)
B57: Шаг | C57: Тип | D57: Значение | E57: Уровень | H57: Невидимая основа | I57: Рост | J57: Падение | K57: Итог
B58: Сегодня | C58: итог | D58: =База!$C$28 -> 192.5 | E58: =D58 -> 192.5 | H58: =0 -> 0 | I58: =IF(C58="шаг",MAX(D58,0),0) -> 0 | J58: =IF(C58="шаг",MAX(-D58,0),0) -> 0 | K58: =IF(C58="итог",D58,0) -> 192.5
B59: Цены на неконтрактные ночи | C59: шаг | D59: =E34 -> 8.67698 | E59: =E58+D59 -> 201.17698 | H59: =IF(C59="итог",0,MIN(E58,E59)) -> 192.5 | I59: =IF(C59="шаг",MAX(D59,0),0) -> 8.67698 | J59: =IF(C59="шаг",MAX(-D59,0),0) -> 0 | K59: =IF(C59="итог",D59,0) -> 0
B60: Микс каналов | C60: шаг | D60: =E35 -> 7.8297872 | E60: =E59+D60 -> 209.00677 | H60: =IF(C60="итог",0,MIN(E59,E60)) -> 201.17698 | I60: =IF(C60="шаг",MAX(D60,0),0) -> 7.8297872 | J60: =IF(C60="шаг",MAX(-D60,0),0) -> 0 | K60: =IF(C60="итог",D60,0) -> 0
B61: Энергия | C61: шаг | D61: =E36 -> 6 | E61: =E60+D61 -> 215.00677 | H61: =IF(C61="итог",0,MIN(E60,E61)) -> 209.00677 | I61: =IF(C61="шаг",MAX(D61,0),0) -> 6 | J61: =IF(C61="шаг",MAX(-D61,0),0) -> 0 | K61: =IF(C61="итог",D61,0) -> 0
B62: Персонал и SOP | C62: шаг | D62: =E37 -> -3 | E62: =E61+D62 -> 212.00677 | H62: =IF(C62="итог",0,MIN(E61,E62)) -> 212.00677 | I62: =IF(C62="шаг",MAX(D62,0),0) -> 0 | J62: =IF(C62="шаг",MAX(-D62,0),0) -> 3 | K62: =IF(C62="итог",D62,0) -> 0
B63: Линия прямых броней | C63: шаг | D63: =E38 -> -5 | E63: =E62+D63 -> 207.00677 | H63: =IF(C63="итог",0,MIN(E62,E63)) -> 207.00677 | I63: =IF(C63="шаг",MAX(D63,0),0) -> 0 | J63: =IF(C63="шаг",MAX(-D63,0),0) -> 5 | K63: =IF(C63="итог",D63,0) -> 0
B64: Налог с доп. выручки | C64: шаг | D64: =E42 -> -0.4620608 | E64: =E63+D64 -> 206.54471 | H64: =IF(C64="итог",0,MIN(E63,E64)) -> 206.54471 | I64: =IF(C64="шаг",MAX(D64,0),0) -> 0 | J64: =IF(C64="шаг",MAX(-D64,0),0) -> 0.4620608 | K64: =IF(C64="итог",D64,0) -> 0
B65: База | C65: итог | D65: =E44 -> 206.54471 | E65: =D65 -> 206.54471 | H65: =IF(C65="итог",0,MIN(E64,E65)) -> 0 | I65: =IF(C65="шаг",MAX(D65,0),0) -> 0 | J65: =IF(C65="шаг",MAX(-D65,0),0) -> 0 | K65: =IF(C65="итог",D65,0) -> 206.54471
B66: Пересмотр цен в контрактах | C66: шаг | D66: =F39 -> 16.15075 | E66: =E65+D66 -> 222.69546 | H66: =IF(C66="итог",0,MIN(E65,E66)) -> 206.54471 | I66: =IF(C66="шаг",MAX(D66,0),0) -> 16.15075 | J66: =IF(C66="шаг",MAX(-D66,0),0) -> 0 | K66: =IF(C66="итог",D66,0) -> 0
B67: Налог с доп. выручки | C67: шаг | D67: =F42-E42 -> -0.688688 | E67: =E66+D67 -> 222.00677 | H67: =IF(C67="итог",0,MIN(E66,E67)) -> 222.00677 | I67: =IF(C67="шаг",MAX(D67,0),0) -> 0 | J67: =IF(C67="шаг",MAX(-D67,0),0) -> 0.688688 | K67: =IF(C67="итог",D67,0) -> 0
B68: Апсайд | C68: итог | D68: =F44 -> 222.00677 | E68: =D68 -> 222.00677 | H68: =IF(C68="итог",0,MIN(E67,E68)) -> 0 | I68: =IF(C68="шаг",MAX(D68,0),0) -> 0 | J68: =IF(C68="шаг",MAX(-D68,0),0) -> 0 | K68: =IF(C68="итог",D68,0) -> 222.00677
B69: Контроль: цепочка шагов приходит ровно в итог «База» и «Апсайд» | D69: =IF(AND(ABS($E$64-$D$65)<0.000001,ABS($E$67-$D$68)<0.000001),"OK","ПРОВЕРИТЬ") -> OK
B70: Ось диаграммы начинается со 170, как на графике кейса; если прибыль станет ниже 170, измените минимум оси.

Sheet Карта
B1: Безубыточность и карта «цена × загрузка»
B2: Разделы 3–4 кейса · прибыль владельца после единого налога, тыс. сом в месяц
B4: 1. Ценность рычагов и безубыточность
B5: Показатель | C5: Значение | D5: Ед. | E5: Как считается
B6: +1% цены | C6: =База!$C$18*0.01*(1-Вводные!$C$40) -> 7.288 | D6: тыс./мес | E6: выручка × 1% × (1 − комиссия − налог)
B7: +1 пункт загрузки | C7: =База!$C$18/(Вводные!$C$14*100)*(1-Вводные!$C$40)-База!$C$24/(Вводные!$C$14*100) -> 7.5670213 | D7: тыс./мес | E7: выручка ÷ загрузка в п.п. × (1 − 8,9%) − расходники ÷ загрузка в п.п.
B8: Выручка при загрузке 100%, по заявленной выручке | C8: =База!$C$18/Вводные!$C$14 -> 851.06383 | D8: тыс./мес | E8: заявленная выручка ÷ текущая загрузка
B9: Выручка при загрузке 100%, по прейскурантному ADR | C9: =Вводные!$C$15*База!$C$6/1000 -> 913.71667 | D9: тыс./мес | E9: ADR × номеро-ночи (k = 1)
B10: Расходники при загрузке 100% | C10: =База!$C$24/Вводные!$C$14 -> 18.617021 | D10: тыс./мес | E10: расходники ÷ текущая загрузка
B11: Безубыточная загрузка после налога (по заявленной выручке) | C11: =База!$C$23/($C$8*(1-Вводные!$C$40)-$C$10) -> 0.68560664 | D11: % | E11: постоянные ÷ (выручка при 100% × (1 − 8,9%) − расходники при 100%)
B12: Безубыточная загрузка после налога (по прейскурантному ADR) | C12: =База!$C$23/($C$9*(1-Вводные!$C$40)-$C$10) -> 0.63751963 | D12: % | E12: то же с выручкой по ADR 3 755
B13: Безубыточная загрузка до налога (по прейскурантному ADR) | C13: =База!$C$23/($C$9*(1-Вводные!$C$34)-$C$10) -> 0.60815737 | D13: % | E13: то же без единого налога
B14: Запас прочности до текущей загрузки (по заявленной выручке) | C14: =(Вводные!$C$14-$C$11)*100 -> 25.439336 | D14: п.п. | E14: текущая загрузка − безубыточная
B15: Запас прочности (по прейскурантному ADR, после налога) | C15: =(Вводные!$C$14-$C$12)*100 -> 30.248037 | D15: п.п.
B16: Запас по выручке: падение, при котором прибыль = 0 | C16: =База!$C$23/(База!$C$18*(1-Вводные!$C$40)-База!$C$24)-1 -> -0.27063124 | D16: % | E16: постоянные ÷ (выручка × (1 − 8,9%) − расходники) − 1; совпадает с запасом по загрузке
B18: 2. Карта: прибыль владельца после налога, тыс. сом/мес
B19: Выручка = загрузка × ADR × (1 + изменение цены) × номеро-ночи × k. Расходники растут с загрузкой; комиссия 4,6% и налог 4,3% — с выручкой; постоянные затраты не меняются.
B20: Текущая загрузка (для подсветки) | C20: =Вводные!$C$14 -> 0.94
B21: Изменение ADR к текущему → | C21: -0.05 | D21: -0.025 | E21: 0 | F21: 0.025 | G21: 0.05 | H21: 0.075 | I21: 0.1
B22: Итоговый ADR, сом → | C22: =Вводные!$C$15*(1+C21) -> 3567.25 | D22: =Вводные!$C$15*(1+D21) -> 3661.125 | E22: =Вводные!$C$15*(1+E21) -> 3755 | F22: =Вводные!$C$15*(1+F21) -> 3848.875 | G22: =Вводные!$C$15*(1+G21) -> 3942.75 | H22: =Вводные!$C$15*(1+H21) -> 4036.625 | I22: =Вводные!$C$15*(1+I21) -> 4130.5
B23: Загрузка ↓
B24: 0.96 | C24: =$B24*Вводные!$C$15*(1+C$21)*База!$C$6*База!$C$11/1000*(1-Вводные!$C$40)-База!$C$23-База!$C$24*$B24/Вводные!$C$14 -> 170.41872 | D24: =$B24*Вводные!$C$15*(1+D$21)*База!$C$6*База!$C$11/1000*(1-Вводные!$C$40)-База!$C$23-База!$C$24*$B24/Вводные!$C$14 -> 189.02638 | E24: =$B24*Вводные!$C$15*(1+E$21)*База!$C$6*База!$C$11/1000*(1-Вводные!$C$40)-База!$C$23-База!$C$24*$B24/Вводные!$C$14 -> 207.63404 | F24: =$B24*Вводные!$C$15*(1+F$21)*База!$C$6*База!$C$11/1000*(1-Вводные!$C$40)-База!$C$23-База!$C$24*$B24/Вводные!$C$14 -> 226.2417 | G24: =$B24*Вводные!$C$15*(1+G$21)*База!$C$6*База!$C$11/1000*(1-Вводные!$C$40)-База!$C$23-База!$C$24*$B24/Вводные!$C$14 -> 244.84936 | H24: =$B24*Вводные!$C$15*(1+H$21)*База!$C$6*База!$C$11/1000*(1-Вводные!$C$40)-База!$C$23-База!$C$24*$B24/Вводные!$C$14 -> 263.45702 | I24: =$B24*Вводные!$C$15*(1+I$21)*База!$C$6*База!$C$11/1000*(1-Вводные!$C$40)-База!$C$23-База!$C$24*$B24/Вводные!$C$14 -> 282.06468
B25: 0.94 | C25: =$B25*Вводные!$C$15*(1+C$21)*База!$C$6*База!$C$11/1000*(1-Вводные!$C$40)-База!$C$23-База!$C$24*$B25/Вводные!$C$14 -> 156.06 | D25: =$B25*Вводные!$C$15*(1+D$21)*База!$C$6*База!$C$11/1000*(1-Вводные!$C$40)-База!$C$23-База!$C$24*$B25/Вводные!$C$14 -> 174.28 | E25: =$B25*Вводные!$C$15*(1+E$21)*База!$C$6*База!$C$11/1000*(1-Вводные!$C$40)-База!$C$23-База!$C$24*$B25/Вводные!$C$14 -> 192.5 | F25: =$B25*Вводные!$C$15*(1+F$21)*База!$C$6*База!$C$11/1000*(1-Вводные!$C$40)-База!$C$23-База!$C$24*$B25/Вводные!$C$14 -> 210.72 | G25: =$B25*Вводные!$C$15*(1+G$21)*База!$C$6*База!$C$11/1000*(1-Вводные!$C$40)-База!$C$23-База!$C$24*$B25/Вводные!$C$14 -> 228.94 | H25: =$B25*Вводные!$C$15*(1+H$21)*База!$C$6*База!$C$11/1000*(1-Вводные!$C$40)-База!$C$23-База!$C$24*$B25/Вводные!$C$14 -> 247.16 | I25: =$B25*Вводные!$C$15*(1+I$21)*База!$C$6*База!$C$11/1000*(1-Вводные!$C$40)-База!$C$23-База!$C$24*$B25/Вводные!$C$14 -> 265.38
B26: 0.92 | C26: =$B26*Вводные!$C$15*(1+C$21)*База!$C$6*База!$C$11/1000*(1-Вводные!$C$40)-База!$C$23-База!$C$24*$B26/Вводные!$C$14 -> 141.70128 | D26: =$B26*Вводные!$C$15*(1+D$21)*База!$C$6*База!$C$11/1000*(1-Вводные!$C$40)-База!$C$23-База!$C$24*$B26/Вводные!$C$14 -> 159.53362 | E26: =$B26*Вводные!$C$15*(1+E$21)*База!$C$6*База!$C$11/1000*(1-Вводные!$C$40)-База!$C$23-База!$C$24*$B26/Вводные!$C$14 -> 177.36596 | F26: =$B26*Вводные!$C$15*(1+F$21)*База!$C$6*База!$C$11/1000*(1-Вводные!$C$40)-База!$C$23-База!$C$24*$B26/Вводные!$C$14 -> 195.1983 | G26: =$B26*Вводные!$C$15*(1+G$21)*База!$C$6*База!$C$11/1000*(1-Вводные!$C$40)-База!$C$23-База!$C$24*$B26/Вводные!$C$14 -> 213.03064 | H26: =$B26*Вводные!$C$15*(1+H$21)*База!$C$6*База!$C$11/1000*(1-Вводные!$C$40)-База!$C$23-База!$C$24*$B26/Вводные!$C$14 -> 230.86298 | I26: =$B26*Вводные!$C$15*(1+I$21)*База!$C$6*База!$C$11/1000*(1-Вводные!$C$40)-База!$C$23-База!$C$24*$B26/Вводные!$C$14 -> 248.69532
B27: 0.9 | C27: =$B27*Вводные!$C$15*(1+C$21)*База!$C$6*База!$C$11/1000*(1-Вводные!$C$40)-База!$C$23-База!$C$24*$B27/Вводные!$C$14 -> 127.34255 | D27: =$B27*Вводные!$C$15*(1+D$21)*База!$C$6*База!$C$11/1000*(1-Вводные!$C$40)-База!$C$23-База!$C$24*$B27/Вводные!$C$14 -> 144.78723 | E27: =$B27*Вводные!$C$15*(1+E$21)*База!$C$6*База!$C$11/1000*(1-Вводные!$C$40)-База!$C$23-База!$C$24*$B27/Вводные!$C$14 -> 162.23191 | F27: =$B27*Вводные!$C$15*(1+F$21)*База!$C$6*База!$C$11/1000*(1-Вводные!$C$40)-База!$C$23-База!$C$24*$B27/Вводные!$C$14 -> 179.6766 | G27: =$B27*Вводные!$C$15*(1+G$21)*База!$C$6*База!$C$11/1000*(1-Вводные!$C$40)-База!$C$23-База!$C$24*$B27/Вводные!$C$14 -> 197.12128 | H27: =$B27*Вводные!$C$15*(1+H$21)*База!$C$6*База!$C$11/1000*(1-Вводные!$C$40)-База!$C$23-База!$C$24*$B27/Вводные!$C$14 -> 214.56596 | I27: =$B27*Вводные!$C$15*(1+I$21)*База!$C$6*База!$C$11/1000*(1-Вводные!$C$40)-База!$C$23-База!$C$24*$B27/Вводные!$C$14 -> 232.01064
B28: 0.88 | C28: =$B28*Вводные!$C$15*(1+C$21)*База!$C$6*База!$C$11/1000*(1-Вводные!$C$40)-База!$C$23-База!$C$24*$B28/Вводные!$C$14 -> 112.98383 | D28: =$B28*Вводные!$C$15*(1+D$21)*База!$C$6*База!$C$11/1000*(1-Вводные!$C$40)-База!$C$23-База!$C$24*$B28/Вводные!$C$14 -> 130.04085 | E28: =$B28*Вводные!$C$15*(1+E$21)*База!$C$6*База!$C$11/1000*(1-Вводные!$C$40)-База!$C$23-База!$C$24*$B28/Вводные!$C$14 -> 147.09787 | F28: =$B28*Вводные!$C$15*(1+F$21)*База!$C$6*База!$C$11/1000*(1-Вводные!$C$40)-База!$C$23-База!$C$24*$B28/Вводные!$C$14 -> 164.15489 | G28: =$B28*Вводные!$C$15*(1+G$21)*База!$C$6*База!$C$11/1000*(1-Вводные!$C$40)-База!$C$23-База!$C$24*$B28/Вводные!$C$14 -> 181.21191 | H28: =$B28*Вводные!$C$15*(1+H$21)*База!$C$6*База!$C$11/1000*(1-Вводные!$C$40)-База!$C$23-База!$C$24*$B28/Вводные!$C$14 -> 198.26894 | I28: =$B28*Вводные!$C$15*(1+I$21)*База!$C$6*База!$C$11/1000*(1-Вводные!$C$40)-База!$C$23-База!$C$24*$B28/Вводные!$C$14 -> 215.32596
B29: 0.84 | C29: =$B29*Вводные!$C$15*(1+C$21)*База!$C$6*База!$C$11/1000*(1-Вводные!$C$40)-База!$C$23-База!$C$24*$B29/Вводные!$C$14 -> 84.266383 | D29: =$B29*Вводные!$C$15*(1+D$21)*База!$C$6*База!$C$11/1000*(1-Вводные!$C$40)-База!$C$23-База!$C$24*$B29/Вводные!$C$14 -> 100.54809 | E29: =$B29*Вводные!$C$15*(1+E$21)*База!$C$6*База!$C$11/1000*(1-Вводные!$C$40)-База!$C$23-База!$C$24*$B29/Вводные!$C$14 -> 116.82979 | F29: =$B29*Вводные!$C$15*(1+F$21)*База!$C$6*База!$C$11/1000*(1-Вводные!$C$40)-База!$C$23-База!$C$24*$B29/Вводные!$C$14 -> 133.11149 | G29: =$B29*Вводные!$C$15*(1+G$21)*База!$C$6*База!$C$11/1000*(1-Вводные!$C$40)-База!$C$23-База!$C$24*$B29/Вводные!$C$14 -> 149.39319 | H29: =$B29*Вводные!$C$15*(1+H$21)*База!$C$6*База!$C$11/1000*(1-Вводные!$C$40)-База!$C$23-База!$C$24*$B29/Вводные!$C$14 -> 165.67489 | I29: =$B29*Вводные!$C$15*(1+I$21)*База!$C$6*База!$C$11/1000*(1-Вводные!$C$40)-База!$C$23-База!$C$24*$B29/Вводные!$C$14 -> 181.9566
B30: 0.8 | C30: =$B30*Вводные!$C$15*(1+C$21)*База!$C$6*База!$C$11/1000*(1-Вводные!$C$40)-База!$C$23-База!$C$24*$B30/Вводные!$C$14 -> 55.548936 | D30: =$B30*Вводные!$C$15*(1+D$21)*База!$C$6*База!$C$11/1000*(1-Вводные!$C$40)-База!$C$23-База!$C$24*$B30/Вводные!$C$14 -> 71.055319 | E30: =$B30*Вводные!$C$15*(1+E$21)*База!$C$6*База!$C$11/1000*(1-Вводные!$C$40)-База!$C$23-База!$C$24*$B30/Вводные!$C$14 -> 86.561702 | F30: =$B30*Вводные!$C$15*(1+F$21)*База!$C$6*База!$C$11/1000*(1-Вводные!$C$40)-База!$C$23-База!$C$24*$B30/Вводные!$C$14 -> 102.06809 | G30: =$B30*Вводные!$C$15*(1+G$21)*База!$C$6*База!$C$11/1000*(1-Вводные!$C$40)-База!$C$23-База!$C$24*$B30/Вводные!$C$14 -> 117.57447 | H30: =$B30*Вводные!$C$15*(1+H$21)*База!$C$6*База!$C$11/1000*(1-Вводные!$C$40)-База!$C$23-База!$C$24*$B30/Вводные!$C$14 -> 133.08085 | I30: =$B30*Вводные!$C$15*(1+I$21)*База!$C$6*База!$C$11/1000*(1-Вводные!$C$40)-База!$C$23-База!$C$24*$B30/Вводные!$C$14 -> 148.58723
B31: 0.75 | C31: =$B31*Вводные!$C$15*(1+C$21)*База!$C$6*База!$C$11/1000*(1-Вводные!$C$40)-База!$C$23-База!$C$24*$B31/Вводные!$C$14 -> 19.652128 | D31: =$B31*Вводные!$C$15*(1+D$21)*База!$C$6*База!$C$11/1000*(1-Вводные!$C$40)-База!$C$23-База!$C$24*$B31/Вводные!$C$14 -> 34.189362 | E31: =$B31*Вводные!$C$15*(1+E$21)*База!$C$6*База!$C$11/1000*(1-Вводные!$C$40)-База!$C$23-База!$C$24*$B31/Вводные!$C$14 -> 48.726596 | F31: =$B31*Вводные!$C$15*(1+F$21)*База!$C$6*База!$C$11/1000*(1-Вводные!$C$40)-База!$C$23-База!$C$24*$B31/Вводные!$C$14 -> 63.26383 | G31: =$B31*Вводные!$C$15*(1+G$21)*База!$C$6*База!$C$11/1000*(1-Вводные!$C$40)-База!$C$23-База!$C$24*$B31/Вводные!$C$14 -> 77.801064 | H31: =$B31*Вводные!$C$15*(1+H$21)*База!$C$6*База!$C$11/1000*(1-Вводные!$C$40)-База!$C$23-База!$C$24*$B31/Вводные!$C$14 -> 92.338298 | I31: =$B31*Вводные!$C$15*(1+I$21)*База!$C$6*База!$C$11/1000*(1-Вводные!$C$40)-База!$C$23-База!$C$24*$B31/Вводные!$C$14 -> 106.87553
B32: 0.7 | C32: =$B32*Вводные!$C$15*(1+C$21)*База!$C$6*База!$C$11/1000*(1-Вводные!$C$40)-База!$C$23-База!$C$24*$B32/Вводные!$C$14 -> -16.244681 | D32: =$B32*Вводные!$C$15*(1+D$21)*База!$C$6*База!$C$11/1000*(1-Вводные!$C$40)-База!$C$23-База!$C$24*$B32/Вводные!$C$14 -> -2.6765957 | E32: =$B32*Вводные!$C$15*(1+E$21)*База!$C$6*База!$C$11/1000*(1-Вводные!$C$40)-База!$C$23-База!$C$24*$B32/Вводные!$C$14 -> 10.891489 | F32: =$B32*Вводные!$C$15*(1+F$21)*База!$C$6*База!$C$11/1000*(1-Вводные!$C$40)-База!$C$23-База!$C$24*$B32/Вводные!$C$14 -> 24.459574 | G32: =$B32*Вводные!$C$15*(1+G$21)*База!$C$6*База!$C$11/1000*(1-Вводные!$C$40)-База!$C$23-База!$C$24*$B32/Вводные!$C$14 -> 38.02766 | H32: =$B32*Вводные!$C$15*(1+H$21)*База!$C$6*База!$C$11/1000*(1-Вводные!$C$40)-База!$C$23-База!$C$24*$B32/Вводные!$C$14 -> 51.595745 | I32: =$B32*Вводные!$C$15*(1+I$21)*База!$C$6*База!$C$11/1000*(1-Вводные!$C$40)-База!$C$23-База!$C$24*$B32/Вводные!$C$14 -> 65.16383
B33: 0.65 | C33: =$B33*Вводные!$C$15*(1+C$21)*База!$C$6*База!$C$11/1000*(1-Вводные!$C$40)-База!$C$23-База!$C$24*$B33/Вводные!$C$14 -> -52.141489 | D33: =$B33*Вводные!$C$15*(1+D$21)*База!$C$6*База!$C$11/1000*(1-Вводные!$C$40)-База!$C$23-База!$C$24*$B33/Вводные!$C$14 -> -39.542553 | E33: =$B33*Вводные!$C$15*(1+E$21)*База!$C$6*База!$C$11/1000*(1-Вводные!$C$40)-База!$C$23-База!$C$24*$B33/Вводные!$C$14 -> -26.943617 | F33: =$B33*Вводные!$C$15*(1+F$21)*База!$C$6*База!$C$11/1000*(1-Вводные!$C$40)-База!$C$23-База!$C$24*$B33/Вводные!$C$14 -> -14.344681 | G33: =$B33*Вводные!$C$15*(1+G$21)*База!$C$6*База!$C$11/1000*(1-Вводные!$C$40)-База!$C$23-База!$C$24*$B33/Вводные!$C$14 -> -1.7457447 | H33: =$B33*Вводные!$C$15*(1+H$21)*База!$C$6*База!$C$11/1000*(1-Вводные!$C$40)-База!$C$23-База!$C$24*$B33/Вводные!$C$14 -> 10.853191 | I33: =$B33*Вводные!$C$15*(1+I$21)*База!$C$6*База!$C$11/1000*(1-Вводные!$C$40)-База!$C$23-База!$C$24*$B33/Вводные!$C$14 -> 23.452128
B34: Выделена жирным и рамкой ячейка «сегодня» (текущая загрузка, изменение цены 0%). Строки и столбцы осей можно менять.

Sheet Сверка
B1: Сверка модели с цифрами, напечатанными в кейсе
B2: Допуск = точность округления в кейсе · «Кейс» — значения из документа (синие), «Модель» — формулы из листов выше
B4: Расхождений: | C4: =COUNTIF(H7:H74,"РАСХОЖДЕНИЕ") -> 0 | D4: ="из "&COUNTA(H7:H74)&" показателей" -> из 68 показателей
B6: Показатель | C6: Раздел | D6: Кейс | E6: Модель | F6: Разница | G6: Допуск | H6: Статус
B7: Затраты, тыс. | C7: 2 | D7: 573.1 | E7: =База!$C$26 -> 573.1 | F7: =E7-D7 -> 0 | G7: 0.05 | H7: =IF(ABS(F7)<=G7+0.000000001,"OK","РАСХОЖДЕНИЕ") -> OK
B8: Единый налог, тыс. | C8: 2 | D8: 34.4 | E8: =База!$C$27 -> 34.4 | F8: =E8-D8 -> 0 | G8: 0.05 | H8: =IF(ABS(F8)<=G8+0.000000001,"OK","РАСХОЖДЕНИЕ") -> OK
B9: Прибыль владельца, тыс. | C9: 2 | D9: 192.5 | E9: =База!$C$28 -> 192.5 | F9: =E9-D9 -> 0 | G9: 0.05 | H9: =IF(ABS(F9)<=G9+0.000000001,"OK","РАСХОЖДЕНИЕ") -> OK
B10: Маржа после налога | C10: 2 | D10: 0.241 | E10: =База!$C$29 -> 0.240625 | F10: =E10-D10 -> -0.000375 | G10: 0.0005 | H10: =IF(ABS(F10)<=G10+0.000000001,"OK","РАСХОЖДЕНИЕ") -> OK
B11: Прибыль после резерва FF&E 5%, тыс. | C11: 2 | D11: 152.5 | E11: =База!$C$32 -> 152.5 | F11: =E11-D11 -> 0 | G11: 0.05 | H11: =IF(ABS(F11)<=G11+0.000000001,"OK","РАСХОЖДЕНИЕ") -> OK
B12: Расчётная выручка, тыс. | C12: 4 | D12: 858.9 | E12: =База!$C$8 -> 858.89367 | F12: =E12-D12 -> -0.0063333333 | G12: 0.05 | H12: =IF(ABS(F12)<=G12+0.000000001,"OK","РАСХОЖДЕНИЕ") -> OK
B13: Коэффициент приведения | C13: 4 | D13: 0.931 | E13: =База!$C$11 -> 0.93143078 | F13: =E13-D13 -> 0.00043078247 | G13: 0.0005 | H13: =IF(ABS(F13)<=G13+0.000000001,"OK","РАСХОЖДЕНИЕ") -> OK
B14: ADR из выручки и загрузки, сом | C14: 4 | D14: 3498 | E14: =База!$C$13 -> 3497.5226 | F14: =E14-D14 -> -0.47741183 | G14: 1 | H14: =IF(ABS(F14)<=G14+0.000000001,"OK","РАСХОЖДЕНИЕ") -> OK
B15: Загрузка из выручки и ADR | C15: 4 | D15: 0.876 | E15: =База!$C$14 -> 0.87554494 | F15: =E15-D15 -> -0.00045506448 | G15: 0.0005 | H15: =IF(ABS(F15)<=G15+0.000000001,"OK","РАСХОЖДЕНИЕ") -> OK
B16: Безубыточная загрузка после налога (по заявленной выручке) | C16: 3 | D16: 0.69 | E16: =Карта!$C$11 -> 0.68560664 | F16: =E16-D16 -> -0.0043933643 | G16: 0.005 | H16: =IF(ABS(F16)<=G16+0.000000001,"OK","РАСХОЖДЕНИЕ") -> OK
B17: Безубыточная загрузка по прейскурантному ADR, после налога | C17: 3 | D17: 0.64 | E17: =Карта!$C$12 -> 0.63751963 | F17: =E17-D17 -> -0.0024803688 | G17: 0.005 | H17: =IF(ABS(F17)<=G17+0.000000001,"OK","РАСХОЖДЕНИЕ") -> OK
B18: Безубыточная загрузка по прейскурантному ADR, до налога | C18: 3 | D18: 0.61 | E18: =Карта!$C$13 -> 0.60815737 | F18: =E18-D18 -> -0.0018426348 | G18: 0.005 | H18: =IF(ABS(F18)<=G18+0.000000001,"OK","РАСХОЖДЕНИЕ") -> OK
B19: Запас прочности, п.п. (заявленная выручка) | C19: 3 | D19: 25 | E19: =Карта!$C$14 -> 25.439336 | F19: =E19-D19 -> 0.43933643 | G19: 0.5 | H19: =IF(ABS(F19)<=G19+0.000000001,"OK","РАСХОЖДЕНИЕ") -> OK
B20: Запас прочности, п.п. (прейскурантный ADR) | C20: 3 | D20: 30 | E20: =Карта!$C$15 -> 30.248037 | F20: =E20-D20 -> 0.24803688 | G20: 0.5 | H20: =IF(ABS(F20)<=G20+0.000000001,"OK","РАСХОЖДЕНИЕ") -> OK
B21: +1% цены, тыс./мес | C21: 3 | D21: 7.3 | E21: =Карта!$C$6 -> 7.288 | F21: =E21-D21 -> -0.012 | G21: 0.05 | H21: =IF(ABS(F21)<=G21+0.000000001,"OK","РАСХОЖДЕНИЕ") -> OK
B22: +1 п.п. загрузки, тыс./мес | C22: 3 | D22: 7.6 | E22: =Карта!$C$7 -> 7.5670213 | F22: =E22-D22 -> -0.032978723 | G22: 0.05 | H22: =IF(ABS(F22)<=G22+0.000000001,"OK","РАСХОЖДЕНИЕ") -> OK
B23: Расходники на ночь, сом | C23: 2 | D23: -77 | E23: =Юнит_экономика!$C$7 -> -76.508307 | F23: =E23-D23 -> 0.49169338 | G23: 1 | H23: =IF(ABS(F23)<=G23+0.000000001,"OK","РАСХОЖДЕНИЕ") -> OK
B24: Комиссия на ночь, сом | C24: 2 | D24: -173 | E24: =Юнит_экономика!$C$8 -> -172.73 | F24: =E24-D24 -> 0.27 | G24: 1 | H24: =IF(ABS(F24)<=G24+0.000000001,"OK","РАСХОЖДЕНИЕ") -> OK
B25: Вклад до налога на ночь, сом | C25: 2 | D25: 3505 | E25: =Юнит_экономика!$C$9 -> 3505.7617 | F25: =E25-D25 -> 0.76169338 | G25: 1 | H25: =IF(ABS(F25)<=G25+0.000000001,"OK","РАСХОЖДЕНИЕ") -> OK
B26: Налог на ночь, сом | C26: 2 | D26: -161 | E26: =Юнит_экономика!$C$10 -> -161.465 | F26: =E26-D26 -> -0.465 | G26: 1 | H26: =IF(ABS(F26)<=G26+0.000000001,"OK","РАСХОЖДЕНИЕ") -> OK
B27: Вклад после налога на ночь, сом | C27: 2 | D27: 3344 | E27: =Юнит_экономика!$C$11 -> 3344.2967 | F27: =E27-D27 -> 0.29669338 | G27: 1 | H27: =IF(ABS(F27)<=G27+0.000000001,"OK","РАСХОЖДЕНИЕ") -> OK
B28: Постоянные затраты на ночь, сом | C28: 2 | D28: -2268 | E28: =Юнит_экономика!$C$12 -> -2268.1434 | F28: =E28-D28 -> -0.14339843 | G28: 1 | H28: =IF(ABS(F28)<=G28+0.000000001,"OK","РАСХОЖДЕНИЕ") -> OK
B29: Прибыль за ночь по заявленному ADR, сом | C29: 2 | D29: 1076 | E29: =Юнит_экономика!$C$13 -> 1076.1533 | F29: =E29-D29 -> 0.15329496 | G29: 1 | H29: =IF(ABS(F29)<=G29+0.000000001,"OK","РАСХОЖДЕНИЕ") -> OK
B30: Сверка с выручкой на ночь, сом | C30: 2 | D30: -234 | E30: =Юнит_экономика!$C$14 -> -234.56192 | F30: =E30-D30 -> -0.56192218 | G30: 1 | H30: =IF(ABS(F30)<=G30+0.000000001,"OK","РАСХОЖДЕНИЕ") -> OK
B31: Прибыль владельца за ночь, сом | C31: 2 | D31: 842 | E31: =Юнит_экономика!$C$15 -> 841.59137 | F31: =E31-D31 -> -0.40862722 | G31: 1 | H31: =IF(ABS(F31)<=G31+0.000000001,"OK","РАСХОЖДЕНИЕ") -> OK
B32: Выручка на номер, тыс. | C32: 2 | D32: 100 | E32: =Юнит_экономика!$C$20 -> 100 | F32: =E32-D32 -> 0 | G32: 0.05 | H32: =IF(ABS(F32)<=G32+0.000000001,"OK","РАСХОЖДЕНИЕ") -> OK
B33: Затраты на номер, тыс. | C33: 2 | D33: -71.6 | E33: =Юнит_экономика!$C$21 -> -71.6375 | F33: =E33-D33 -> -0.0375 | G33: 0.05 | H33: =IF(ABS(F33)<=G33+0.000000001,"OK","РАСХОЖДЕНИЕ") -> OK
B34: Налог на номер, тыс. | C34: 2 | D34: -4.3 | E34: =Юнит_экономика!$C$22 -> -4.3 | F34: =E34-D34 -> 0 | G34: 0.05 | H34: =IF(ABS(F34)<=G34+0.000000001,"OK","РАСХОЖДЕНИЕ") -> OK
B35: Прибыль на номер, тыс. | C35: 2 | D35: 24.1 | E35: =Юнит_экономика!$C$23 -> 24.0625 | F35: =E35-D35 -> -0.0375 | G35: 0.05 | H35: =IF(ABS(F35)<=G35+0.000000001,"OK","РАСХОЖДЕНИЕ") -> OK
B36: Стресс «Выручка −10%»: прибыль, тыс. | C36: 5 | D36: 121.4 | E36: =Стресс_тесты!$N$17 -> 121.37 | F36: =E36-D36 -> -0.03 | G36: 0.05 | H36: =IF(ABS(F36)<=G36+0.000000001,"OK","РАСХОЖДЕНИЕ") -> OK
B37: Стресс «Выручка −10%»: Δ, тыс. | C37: 5 | D37: -71.1 | E37: =Стресс_тесты!$O$17 -> -71.13 | F37: =E37-D37 -> -0.03 | G37: 0.05 | H37: =IF(ABS(F37)<=G37+0.000000001,"OK","РАСХОЖДЕНИЕ") -> OK
B38: Стресс «Выручка −10%»: маржа | C38: 5 | D38: 0.169 | E38: =Стресс_тесты!$Q$17 -> 0.16856944 | F38: =E38-D38 -> -0.00043055556 | G38: 0.0005 | H38: =IF(ABS(F38)<=G38+0.000000001,"OK","РАСХОЖДЕНИЕ") -> OK
B39: Стресс «Выручка −15%»: прибыль, тыс. | C39: 5 | D39: 85.8 | E39: =Стресс_тесты!$N$18 -> 85.805 | F39: =E39-D39 -> 0.005 | G39: 0.05 | H39: =IF(ABS(F39)<=G39+0.000000001,"OK","РАСХОЖДЕНИЕ") -> OK
B40: Стресс «Выручка −15%»: Δ, тыс. | C40: 5 | D40: -106.7 | E40: =Стресс_тесты!$O$18 -> -106.695 | F40: =E40-D40 -> 0.005 | G40: 0.05 | H40: =IF(ABS(F40)<=G40+0.000000001,"OK","РАСХОЖДЕНИЕ") -> OK
B41: Стресс «Выручка −15%»: маржа | C41: 5 | D41: 0.126 | E41: =Стресс_тесты!$Q$18 -> 0.12618382 | F41: =E41-D41 -> 0.00018382353 | G41: 0.0005 | H41: =IF(ABS(F41)<=G41+0.000000001,"OK","РАСХОЖДЕНИЕ") -> OK
B42: Стресс «Потеря двух мобильных операторов»: прибыль, тыс. | C42: 5 | D42: 132.7 | E42: =Стресс_тесты!$N$19 -> 132.652 | F42: =E42-D42 -> -0.048 | G42: 0.05 | H42: =IF(ABS(F42)<=G42+0.000000001,"OK","РАСХОЖДЕНИЕ") -> OK
B43: Стресс «Потеря двух мобильных операторов»: Δ, тыс. | C43: 5 | D43: -59.8 | E43: =Стресс_тесты!$O$19 -> -59.848 | F43: =E43-D43 -> -0.048 | G43: 0.05 | H43: =IF(ABS(F43)<=G43+0.000000001,"OK","РАСХОЖДЕНИЕ") -> OK
B44: Стресс «Потеря двух мобильных операторов»: маржа | C44: 5 | D44: 0.18 | E44: =Стресс_тесты!$Q$19 -> 0.1802337 | F44: =E44-D44 -> 0.00023369565 | G44: 0.0005 | H44: =IF(ABS(F44)<=G44+0.000000001,"OK","РАСХОЖДЕНИЕ") -> OK
B45: Стресс «Аренда +10%»: прибыль, тыс. | C45: 5 | D45: 157.5 | E45: =Стресс_тесты!$N$20 -> 157.5 | F45: =E45-D45 -> 0 | G45: 0.05 | H45: =IF(ABS(F45)<=G45+0.000000001,"OK","РАСХОЖДЕНИЕ") -> OK
B46: Стресс «Аренда +10%»: Δ, тыс. | C46: 5 | D46: -35 | E46: =Стресс_тесты!$O$20 -> -35 | F46: =E46-D46 -> 0 | G46: 0.05 | H46: =IF(ABS(F46)<=G46+0.000000001,"OK","РАСХОЖДЕНИЕ") -> OK
B47: Стресс «Аренда +10%»: маржа | C47: 5 | D47: 0.197 | E47: =Стресс_тесты!$Q$20 -> 0.196875 | F47: =E47-D47 -> -0.000125 | G47: 0.0005 | H47: =IF(ABS(F47)<=G47+0.000000001,"OK","РАСХОЖДЕНИЕ") -> OK
B48: Стресс «Электричество +20%»: прибыль, тыс. | C48: 5 | D48: 180.5 | E48: =Стресс_тесты!$N$21 -> 180.5 | F48: =E48-D48 -> 0 | G48: 0.05 | H48: =IF(ABS(F48)<=G48+0.000000001,"OK","РАСХОЖДЕНИЕ") -> OK
B49: Стресс «Электричество +20%»: Δ, тыс. | C49: 5 | D49: -12 | E49: =Стресс_тесты!$O$21 -> -12 | F49: =E49-D49 -> 0 | G49: 0.05 | H49: =IF(ABS(F49)<=G49+0.000000001,"OK","РАСХОЖДЕНИЕ") -> OK
B50: Стресс «Электричество +20%»: маржа | C50: 5 | D50: 0.226 | E50: =Стресс_тесты!$Q$21 -> 0.225625 | F50: =E50-D50 -> -0.000375 | G50: 0.0005 | H50: =IF(ABS(F50)<=G50+0.000000001,"OK","РАСХОЖДЕНИЕ") -> OK
B51: Стресс «Управляющий за 60 тыс.»: прибыль, тыс. | C51: 5 | D51: 132.5 | E51: =Стресс_тесты!$N$22 -> 132.5 | F51: =E51-D51 -> 0 | G51: 0.05 | H51: =IF(ABS(F51)<=G51+0.000000001,"OK","РАСХОЖДЕНИЕ") -> OK
B52: Стресс «Управляющий за 60 тыс.»: Δ, тыс. | C52: 5 | D52: -60 | E52: =Стресс_тесты!$O$22 -> -60 | F52: =E52-D52 -> 0 | G52: 0.05 | H52: =IF(ABS(F52)<=G52+0.000000001,"OK","РАСХОЖДЕНИЕ") -> OK
B53: Стресс «Управляющий за 60 тыс.»: маржа | C53: 5 | D53: 0.166 | E53: =Стресс_тесты!$Q$22 -> 0.165625 | F53: =E53-D53 -> -0.000375 | G53: 0.0005 | H53: =IF(ABS(F53)<=G53+0.000000001,"OK","РАСХОЖДЕНИЕ") -> OK
B54: Рычаг 2. Цены, тыс./мес | C54: 6 | D54: 8.7 | E54: =Мост_прибыли!$E$34 -> 8.67698 | F54: =E54-D54 -> -0.02302 | G54: 0.05 | H54: =IF(ABS(F54)<=G54+0.000000001,"OK","РАСХОЖДЕНИЕ") -> OK
B55: Рычаг 3. Каналы, тыс./мес | C55: 6 | D55: 7.8 | E55: =Мост_прибыли!$E$35 -> 7.8297872 | F55: =E55-D55 -> 0.029787234 | G55: 0.05 | H55: =IF(ABS(F55)<=G55+0.000000001,"OK","РАСХОЖДЕНИЕ") -> OK
B56: Рычаг 5. Энергия, тыс./мес | C56: 6 | D56: 6 | E56: =Мост_прибыли!$E$36 -> 6 | F56: =E56-D56 -> 0 | G56: 0.05 | H56: =IF(ABS(F56)<=G56+0.000000001,"OK","РАСХОЖДЕНИЕ") -> OK
B57: Гигиена, тыс./мес | C57: 6 | D57: -8 | E57: =(Мост_прибыли!$E$37+Мост_прибыли!$E$38) -> -8 | F57: =E57-D57 -> 0 | G57: 0.05 | H57: =IF(ABS(F57)<=G57+0.000000001,"OK","РАСХОЖДЕНИЕ") -> OK
B58: Рычаг 4. Пересмотр контрактов, тыс./мес | C58: 6 | D58: 16.2 | E58: =Мост_прибыли!$F$39 -> 16.15075 | F58: =E58-D58 -> -0.04925 | G58: 0.06 | H58: =IF(ABS(F58)<=G58+0.000000001,"OK","РАСХОЖДЕНИЕ") -> OK
B59: База: Δ операционной прибыли, тыс. | C59: 6 | D59: 14.5 | E59: =Мост_прибыли!$E$40 -> 14.506767 | F59: =E59-D59 -> 0.006767234 | G59: 0.05 | H59: =IF(ABS(F59)<=G59+0.000000001,"OK","РАСХОЖДЕНИЕ") -> OK
B60: Апсайд: Δ операционной прибыли, тыс. | C60: 6 | D60: 30.6 | E60: =Мост_прибыли!$F$40 -> 30.657517 | F60: =E60-D60 -> 0.057517234 | G60: 0.1 | H60: =IF(ABS(F60)<=G60+0.000000001,"OK","РАСХОЖДЕНИЕ") -> OK
B61: База: Δ прибыли после налога, тыс. | C61: 6 | D61: 14 | E61: =Мост_прибыли!$E$43 -> 14.044706 | F61: =E61-D61 -> 0.044706434 | G61: 0.05 | H61: =IF(ABS(F61)<=G61+0.000000001,"OK","РАСХОЖДЕНИЕ") -> OK
B62: Апсайд: Δ прибыли после налога, тыс. | C62: 6 | D62: 29.5 | E62: =Мост_прибыли!$F$43 -> 29.506768 | F62: =E62-D62 -> 0.006768434 | G62: 0.05 | H62: =IF(ABS(F62)<=G62+0.000000001,"OK","РАСХОЖДЕНИЕ") -> OK
B63: Прибыль владельца в базе, тыс. | C63: 6 | D63: 206.5 | E63: =Мост_прибыли!$E$44 -> 206.54471 | F63: =E63-D63 -> 0.044706434 | G63: 0.05 | H63: =IF(ABS(F63)<=G63+0.000000001,"OK","РАСХОЖДЕНИЕ") -> OK
B64: Прибыль владельца в апсайде, тыс. | C64: 6 | D64: 222 | E64: =Мост_прибыли!$F$44 -> 222.00677 | F64: =E64-D64 -> 0.006768434 | G64: 0.05 | H64: =IF(ABS(F64)<=G64+0.000000001,"OK","РАСХОЖДЕНИЕ") -> OK
B65: Консервативный: Δ до налога, тыс. (≈0) | C65: 6 | D65: 0 | E65: =Мост_прибыли!$D$40 -> 0.33100362 | F65: =E65-D65 -> 0.33100362 | G65: 0.5 | H65: =IF(ABS(F65)<=G65+0.000000001,"OK","РАСХОЖДЕНИЕ") -> OK
B66: Окупаемость базы, мес. | C66: 6 | D66: 13 | E66: =Мост_прибыли!$E$47 -> 12.816217 | F66: =E66-D66 -> -0.18378338 | G66: 0.5 | H66: =IF(ABS(F66)<=G66+0.000000001,"OK","РАСХОЖДЕНИЕ") -> OK
B67: Окупаемость апсайда, мес. | C67: 6 | D67: 6 | E67: =Мост_прибыли!$F$47 -> 6.1002953 | F67: =E67-D67 -> 0.10029527 | G67: 0.5 | H67: =IF(ABS(F67)<=G67+0.000000001,"OK","РАСХОЖДЕНИЕ") -> OK
B68: Чистый эффект базы за 36 мес., млн | C68: 6 | D68: 0.3 | E68: =(Мост_прибыли!$E$48/1000) -> 0.32560943 | F68: =E68-D68 -> 0.025609432 | G68: 0.05 | H68: =IF(ABS(F68)<=G68+0.000000001,"OK","РАСХОЖДЕНИЕ") -> OK
B69: Чистый эффект апсайда за 36 мес., млн | C69: 6 | D69: 0.9 | E69: =(Мост_прибыли!$F$48/1000) -> 0.88224366 | F69: =E69-D69 -> -0.017756336 | G69: 0.05 | H69: =IF(ABS(F69)<=G69+0.000000001,"OK","РАСХОЖДЕНИЕ") -> OK
B70: Потеря контрактного объёма, при которой рычаг 4 = 0 | C70: 6 | D70: 0.037 | E70: =Мост_прибыли!$D$54 -> 0.036805112 | F70: =E70-D70 -> -0.00019488818 | G70: 0.0005 | H70: =IF(ABS(F70)<=G70+0.000000001,"OK","РАСХОЖДЕНИЕ") -> OK
B71: Защита аренды: низ, тыс./мес | C71: 1 | D71: 17.5 | E71: =Мост_прибыли!$D$52 -> 17.5 | F71: =E71-D71 -> 0 | G71: 0.05 | H71: =IF(ABS(F71)<=G71+0.000000001,"OK","РАСХОЖДЕНИЕ") -> OK
B72: Защита аренды: верх, тыс./мес | C72: 1 | D72: 35 | E72: =Мост_прибыли!$E$52 -> 35 | F72: =E72-D72 -> 0 | G72: 0.05 | H72: =IF(ABS(F72)<=G72+0.000000001,"OK","РАСХОЖДЕНИЕ") -> OK
B73: Защита аренды за 3 года: низ, млн | C73: 1 | D73: 0.6 | E73: =(Мост_прибыли!$D$53/1000) -> 0.63 | F73: =E73-D73 -> 0.03 | G73: 0.05 | H73: =IF(ABS(F73)<=G73+0.000000001,"OK","РАСХОЖДЕНИЕ") -> OK
B74: Защита аренды за 3 года: верх, млн | C74: 1 | D74: 1.3 | E74: =(Мост_прибыли!$E$53/1000) -> 1.26 | F74: =E74-D74 -> -0.04 | G74: 0.05 | H74: =IF(ABS(F74)<=G74+0.000000001,"OK","РАСХОЖДЕНИЕ") -> OK
B76: Замечания к самому кейсу
B77: • Маржа до единого налога: в тексте кейса «≈29%», по его же цифрам (800 − 573,1) ÷ 800 = 28,4%. В проверки не включена.
B78: • Рычаг 4: точное значение 16,15 → в кейсе показано 16,2; сумма «база + апсайд» 30,66 в кейсе округлена до 30,6 (допуск 0,1).
B79: • Цифры «на ночь» в кейсе получены из уже округлённых слагаемых, поэтому отличаются от точного расчёта на ±1 сом (допуск 1).
B80: • Безубыточность ≈69% в кейсе — округление от 68,6%; допуск 0,5 п.п.
